[
    {
        "page_label": "Register Form",
        "field": [
            {
                "field_id": "name",
                "field_label": "Name",
                "field_type": "text",
                "field_placeholder": "Enter your Name",
                "field_required": true
            },
            {
                "field_id": "full_name",
                "field_label": "Full Name",
                "field_type": "text",
                "field_placeholder": "Enter your fullname",
                "field_required": true
            },
            {
                "field_id": "user_name",
                "field_label": "User Name",
                "field_type": "text",
                "field_placeholder": "Enter your username",
                "field_required": true
            },
            {
                "field_id": "phone_number",
                "field_label": "Phone Number",
                "field_type": "tel",
                "field_placeholder": "Enter your phone number",
                "field_required": true
            },
            {
                "field_id": "email",
                "field_label": "Email",
                "field_type": "email",
                "field_placeholder": "Enter your email",
                "field_required": true
            },
            
            {
                "field_id": "password",
                "field_label": "Password",
                "field_type": "password",
                "field_placeholder": "Enter your password",
                "field_required": true
            }
        ]
    }
]